ver14/__init__.py
ver14/images/__init__.py
ver14/images/about1.png
ver14/images/cs.png
ver14/images/doc.png
ver14/images/folder_icon.png
ver14/images/initial1.png
ver14/images/java1.png
ver14/images/logo.png
ver14/images/py.png
ver14/settings/UT_Settings.ini
ver14/settings/__init__.py
ver14/src/AIUT.py
ver14/src/AIUT_Core_CSharp.py
ver14/src/AIUT_Core_Java.py
ver14/src/AIUT_Core_Python.py
ver14/src/AIUT_SingleFile.py
ver14/src/OpenAI_Pricing.py
ver14/src/__init__.py
ver14/src/sub.py
ver14-0.1.dist-info/METADATA
ver14-0.1.dist-info/WHEEL
ver14-0.1.dist-info/entry_points.txt
ver14-0.1.dist-info/license.txt
ver14-0.1.dist-info/top_level.txt
ver14-0.1.dist-info/RECORD
