Metadata-Version: 2.1
Name: ver14
Version: 0.1
License-File: license.txt
Requires-Dist: Pillow
Requires-Dist: openai
